<Properties StartupConfiguration="{6C1FB0D6-28F0-4F5D-A647-0E8896018FFC}|Default">
  <MonoDevelop.Ide.Workbench>
    <Pads>
      <Pad Id="ProjectPad">
        <State name="__root__">
          <Node name="dotnet-5" expanded="True">
            <Node name="dotnet-5" expanded="True">
              <Node name="Controllers" expanded="True">
                <Node name="FilesStorageController.cs" selected="True" />
              </Node>
              <Node name="Models" expanded="True" />
            </Node>
          </Node>
        </State>
      </Pad>
    </Pads>
  </MonoDevelop.Ide.Workbench>
  <MonoDevelop.Ide.DebuggingService.PinnedWatches />
  <MonoDevelop.Ide.Workspace ActiveConfiguration="Debug" />
  <MonoDevelop.Ide.ItemProperties.dotnet-5 PreferredExecutionTarget="/Applications/Google Chrome.app" />
  <MonoDevelop.Ide.DebuggingService.Breakpoints>
    <BreakpointStore />
  </MonoDevelop.Ide.DebuggingService.Breakpoints>
  <MultiItemStartupConfigurations />
</Properties>